textual_email_client/__about__.py
textual_email_client/__init__.py
textual_email_client/email_client.py
textual_email_client/entry_points.py
textual_email_client-1.0.1.dist-info/METADATA
textual_email_client-1.0.1.dist-info/WHEEL
textual_email_client-1.0.1.dist-info/entry_points.txt
textual_email_client-1.0.1.dist-info/licenses/LICENSE.txt
textual_email_client-1.0.1.dist-info/RECORD
