Metadata-Version: 2.3
Name: textual-email-client
Version: 1.0.1
Summary: A Textual based Email Client powered by Nylas
Project-URL: Documentation, https://github.com/nylas-samples/textual_terminal_email_client/blob/Python_V3/README.md
Project-URL: Issues, https://github.com/nylas-samples/textual_terminal_email_client/issues
Project-URL: Source, https://github.com/nylas-samples/textual_terminal_email_client
Author-email: Blag <alvaro.t@nylas.com>
License-Expression: MIT
License-File: LICENSE.txt
Classifier: Development Status :: 4 - Beta
Classifier: Programming Language :: Python
Classifier: Programming Language :: Python :: 3.8
Classifier: Programming Language :: Python :: 3.9
Classifier: Programming Language :: Python :: 3.10
Classifier: Programming Language :: Python :: 3.11
Classifier: Programming Language :: Python :: 3.12
Classifier: Programming Language :: Python :: Implementation :: CPython
Classifier: Programming Language :: Python :: Implementation :: PyPy
Requires-Python: >=3.8
Requires-Dist: beautifulsoup4==4.12.3
Requires-Dist: nylas==6.3.0
Requires-Dist: python-dotenv==1.0.1
Requires-Dist: rich==13.7.1
Requires-Dist: textual==0.76.0
